LICENSE
MANIFEST.in
README.md
setup.py
clusterval/__init__.py
clusterval/external.py
clusterval/internal.py
clusterval/validation.py
clusterval.egg-info/PKG-INFO
clusterval.egg-info/SOURCES.txt
clusterval.egg-info/dependency_links.txt
clusterval.egg-info/requires.txt
clusterval.egg-info/top_level.txt
clusterval/datasets/__init__.py
clusterval/datasets/animals.csv
clusterval/datasets/datasets.py
clusterval/datasets/test_khan.csv
clusterval/datasets/train_khan.csv
clusterval/datasets/vote_repub.csv