Metadata-Version: 2.1
Name: clusterval
Version: 1.0.5
Summary: Package useful for clustering validation
Home-page: https://github.com/Nuno09/clusterval
Author: Nuno Silva
Author-email: nuno.da.silva@tecnico.ulisboa.pt
License: LICENSE
Platform: UNKNOWN
